{"chunk_definitions":[{"chunk_id":"csetup_chunk","chunk_label":"setup","expansion_state":0,"options":{"engine":"r","include":false,"label":"setup"},"row":9,"row_count":1,"visible":true},{"chunk_id":"c7kj4ksf92lsn","chunk_label":"importing","expansion_state":0,"options":{"engine":"r","label":"importing"},"row":40,"row_count":1,"visible":true},{"chunk_id":"chttsj8pk2zl2","chunk_label":"unnamed-chunk-1","expansion_state":0,"options":{"engine":"r","label":"unnamed-chunk-2"},"row":51,"row_count":1,"visible":true},{"chunk_id":"c4q6oteqhagaa","chunk_label":"calculatingRc","expansion_state":0,"options":{"echo":false,"engine":"r","label":"calculatingRc"},"row":69,"row_count":1,"visible":true},{"chunk_id":"cecibjkakt4tv","chunk_label":"subsetdata","expansion_state":0,"options":{"engine":"r","label":"subsetdata"},"row":78,"row_count":1,"visible":true},{"chunk_id":"co1hsryg9xz7c","chunk_label":"converttimes","expansion_state":0,"options":{"engine":"r","label":"converttimes"},"row":96,"row_count":1,"visible":true},{"chunk_id":"ccfxnzbc2opmx","chunk_label":"Et_alignments","expansion_state":0,"options":{"engine":"r","label":"Et_alignments"},"row":123,"row_count":1,"visible":true},{"chunk_id":"cqqfh7yflppcb","chunk_label":"Oldsection","expansion_state":0,"options":{"engine":"r","label":"Oldsection"},"row":207,"row_count":1,"visible":true},{"chunk_id":"cd8me5lkb8dwp","chunk_label":"RcTest","expansion_state":0,"options":{"engine":"r","label":"RcTest"},"row":217,"row_count":1,"visible":true},{"chunk_id":"cqa4ldcqifbqz","chunk_label":"calculatingK","expansion_state":0,"options":{"engine":"r","label":"calculatingK"},"row":250,"row_count":1,"visible":true},{"chunk_id":"c15egyv59zlvr","chunk_label":"unnamed-chunk-3","expansion_state":0,"options":{"engine":"r","label":"unnamed-chunk-3"},"row":271,"row_count":1,"visible":true},{"chunk_id":"ceyv7faiv0qw2","chunk_label":"unnamed-chunk-4","expansion_state":0,"options":{"engine":"r","label":"unnamed-chunk-4"},"row":284,"row_count":1,"visible":true},{"chunk_id":"c05m89mlctsd4","chunk_label":"unnamed-chunk-5","expansion_state":0,"options":{"engine":"r","label":"unnamed-chunk-5"},"row":293,"row_count":1,"visible":true},{"chunk_id":"cpw4wuxwm7znu","chunk_label":"figure","expansion_state":0,"options":{"echo":"T","engine":"r","label":"figure"},"row":301,"row_count":1,"visible":true},{"chunk_id":"c9vgeeof1y2nd","chunk_label":"loop","expansion_state":0,"options":{"engine":"r","label":"loop"},"row":322,"row_count":1,"visible":true},{"chunk_id":"c85v14vkmouw0","chunk_label":"loopwrite","expansion_state":0,"options":{"engine":"r","label":"loopwrite"},"row":344,"row_count":1,"visible":true}],"doc_write_time":1471143175}